tbraille/__init__.py
tbraille/__main__.py
tbraille/board.py
tbraille-1.2.4.dist-info/entry_points.txt
tbraille-1.2.4.dist-info/LICENSE
tbraille-1.2.4.dist-info/WHEEL
tbraille-1.2.4.dist-info/METADATA
tbraille-1.2.4.dist-info/RECORD
